{
  "id": 73129,
  "type": "WQ",
  "titleTextMapHash": 3060051535,
  "descTextMapHash": 2621676558,
  "luaPath": "Actor/Quest/WQ73129",
  "showType": "QUEST_HIDDEN",
  "rewardIdList": [210007],
  "subQuests": [
    {
      "subId": 7312901,
      "mainId": 73129,
      "order": 1,
      "descTextMapHash": 3802745172,
      "failCondComb": "QUEST_HIDDEN",
      "acceptCondComb": "LOGIC_AND",
      "finishCondComb": "LOGIC_NONE",
      "failParentShow": "QUEST_HIDDEN",
      "acceptCond": [
        {
          "type": "QUEST_COND_PLAYER_ENTER_REGION",
          "param": [133303546, 546002],
          "param_str": ""
        },
        {
          "type": "QUEST_COND_QUEST_GLOBAL_VAR_EQUAL",
          "param": [73101, 1],
          "param_str": ""
        }
      ],
      "finishCond": [
        {
          "type": "QUEST_CONTENT_GAME_TIME_TICK",
          "param": [0, 0],
          "param_str": "0,24"
        }
      ],
      "failCond": [],
      "beginExec": [],
      "finishExec": [],
      "failExec": [],
      "guide": {}
    },
    {
      "subId": 7312902,
      "mainId": 73129,
      "order": 2,
      "descTextMapHash": 4270379884,
      "failCondComb": "QUEST_HIDDEN",
      "acceptCondComb": "LOGIC_AND",
      "finishCondComb": "LOGIC_NONE",
      "failParentShow": "QUEST_HIDDEN",
      "acceptCond": [
        {
          "type": "QUEST_COND_STATE_EQUAL",
          "param": [7312901, 3],
          "param_str": ""
        },
        {
          "type": "QUEST_COND_QUEST_GLOBAL_VAR_EQUAL",
          "param": [73102, 0],
          "param_str": ""
        }
      ],
      "finishCond": [
        {
          "type": "QUEST_CONTENT_QUEST_STATE_EQUAL",
          "param": [7300309, 3],
          "param_str": ""
        }
      ],
      "failCond": [],
      "beginExec": [],
      "finishExec": [],
      "failExec": [],
      "guide": {}
    },
    {
      "subId": 7312903,
      "mainId": 73129,
      "order": 4,
      "descTextMapHash": 2598027996,
      "failCondComb": "QUEST_HIDDEN",
      "acceptCondComb": "LOGIC_AND",
      "finishCondComb": "LOGIC_NONE",
      "failParentShow": "QUEST_HIDDEN",
      "acceptCond": [
        {
          "type": "QUEST_COND_STATE_EQUAL",
          "param": [7312901, 3],
          "param_str": ""
        },
        {
          "type": "QUEST_COND_STATE_EQUAL",
          "param": [7302515, 3],
          "param_str": ""
        }
      ],
      "finishCond": [
        {
          "type": "QUEST_CONTENT_COMPLETE_TALK",
          "param": [7312901, 0],
          "param_str": ""
        }
      ],
      "failCond": [],
      "beginExec": [
        {
          "type": "QUEST_EXEC_ACTIVE_ITEM_GIVING",
          "param": ["7312903", "0"],
          "param_str": ""
        }
      ],
      "finishExec": [],
      "failExec": [],
      "guide": {}
    },
    {
      "subId": 7312904,
      "mainId": 73129,
      "order": 5,
      "descTextMapHash": 2596433484,
      "failCondComb": "QUEST_HIDDEN",
      "acceptCondComb": "LOGIC_NONE",
      "finishCondComb": "LOGIC_NONE",
      "failParentShow": "QUEST_HIDDEN",
      "acceptCond": [
        {
          "type": "QUEST_COND_STATE_EQUAL",
          "param": [7312903, 3],
          "param_str": ""
        }
      ],
      "finishCond": [
        {
          "type": "QUEST_CONTENT_FINISH_ITEM_GIVING",
          "param": [7312903, 0],
          "param_str": ""
        }
      ],
      "failCond": [],
      "beginExec": [],
      "finishExec": [],
      "failExec": [],
      "guide": {}
    },
    {
      "subId": 7312905,
      "mainId": 73129,
      "order": 6,
      "descTextMapHash": 1490968556,
      "failCondComb": "QUEST_HIDDEN",
      "acceptCondComb": "LOGIC_NONE",
      "finishCondComb": "LOGIC_NONE",
      "failParentShow": "QUEST_HIDDEN",
      "acceptCond": [
        {
          "type": "QUEST_COND_STATE_EQUAL",
          "param": [7312904, 3],
          "param_str": ""
        }
      ],
      "finishCond": [
        {
          "type": "QUEST_CONTENT_COMPLETE_TALK",
          "param": [7312903, 0],
          "param_str": ""
        }
      ],
      "failCond": [],
      "beginExec": [],
      "finishExec": [
        {
          "type": "QUEST_EXEC_INC_QUEST_GLOBAL_VAR",
          "param": ["73100", "1"],
          "param_str": ""
        },
        {
          "type": "QUEST_EXEC_REFRESH_GROUP_SUITE",
          "param": ["3", "133303546,2"],
          "param_str": ""
        }
      ],
      "failExec": [],
      "guide": {}
    },
    {
      "subId": 7312906,
      "mainId": 73129,
      "order": 3,
      "descTextMapHash": 747100004,
      "failCondComb": "QUEST_HIDDEN",
      "acceptCondComb": "LOGIC_AND",
      "finishCondComb": "LOGIC_NONE",
      "failParentShow": "QUEST_HIDDEN",
      "acceptCond": [
        {
          "type": "QUEST_COND_STATE_EQUAL",
          "param": [7312901, 3],
          "param_str": ""
        },
        {
          "type": "QUEST_COND_QUEST_GLOBAL_VAR_EQUAL",
          "param": [73102, 1],
          "param_str": ""
        },
        {
          "type": "QUEST_COND_QUEST_GLOBAL_VAR_EQUAL",
          "param": [73103, 0],
          "param_str": ""
        }
      ],
      "finishCond": [
        {
          "type": "QUEST_CONTENT_QUEST_STATE_EQUAL",
          "param": [7302515, 3],
          "param_str": ""
        }
      ],
      "failCond": [],
      "beginExec": [],
      "finishExec": [],
      "failExec": [],
      "guide": {}
    }
  ],
  "talks": [
    {
      "id": 7312901,
      "beginWay": "TALK_BEGIN_MANUAL",
      "beginCondComb": "LOGIC_AND",
      "beginCond": [
        {
          "type": "QUEST_COND_STATE_EQUAL",
          "param": ["7312903", "2"],
          "param_str": ""
        },
        {
          "type": "QUEST_COND_ITEM_GIVING_ACTIVED",
          "param": ["7312903", "0"],
          "param_str": ""
        }
      ],
      "priority": 5,
      "initDialog": 731290101,
      "npcId": [20695],
      "performCfg": "",
      "heroTalk": "TALK_HERO_MAIN",
      "questId": 73129,
      "prePerformCfg": ""
    },
    {
      "id": 7312902,
      "beginWay": "TALK_BEGIN_MANUAL",
      "beginCondComb": "LOGIC_AND",
      "beginCond": [
        {
          "type": "QUEST_COND_STATE_EQUAL",
          "param": ["7312904", "2"],
          "param_str": ""
        },
        {
          "type": "QUEST_COND_STATE_EQUAL",
          "param": ["7312903", "3"],
          "param_str": ""
        },
        {
          "type": "QUEST_COND_ITEM_GIVING_ACTIVED",
          "param": ["7312903", "0"],
          "param_str": ""
        }
      ],
      "priority": 5,
      "initDialog": 731290201,
      "npcId": [20695],
      "performCfg": "",
      "heroTalk": "TALK_HERO_MAIN",
      "questId": 73129,
      "prePerformCfg": ""
    },
    {
      "id": 7312903,
      "beginWay": "TALK_BEGIN_MANUAL",
      "beginCond": [
        {
          "type": "QUEST_COND_STATE_EQUAL",
          "param": ["7312905", "2"],
          "param_str": ""
        }
      ],
      "priority": 5,
      "initDialog": 731290301,
      "npcId": [20695],
      "performCfg": "",
      "heroTalk": "TALK_HERO_MAIN",
      "questId": 73129,
      "prePerformCfg": ""
    }
  ]
}
